robot_utils/__init__.py
robot_utils/config_utils.py
robot_utils/data_utils.py
robot_utils/logging_utils.py
robot_utils/pose_utils.py
robot_utils/torch_utils.py
robot_utils/video_utils.py
robot_utils-0.1.1.dist-info/METADATA
robot_utils-0.1.1.dist-info/WHEEL
robot_utils-0.1.1.dist-info/top_level.txt
robot_utils-0.1.1.dist-info/RECORD
