Metadata-Version: 2.4
Name: robot-utils
Version: 0.1.1
Summary: Frequently used utility functions for robot learning research
Author-email: Yihuai Gao <davidgao1013@gmail.com>
Project-URL: Homepage, https://github.com/yihuai-gao/robot-utils
Classifier: Programming Language :: Python :: 3
Classifier: License :: OSI Approved :: MIT License
Classifier: Operating System :: OS Independent
